{
  "coord": {
    "lon": 139.6425,
    "lat": 35.4478
  },
  "list": [
    {
      "main": {
        "aqi": 3
      },
      "components": {
        "co": 200.13,
        "no": 3.27,
        "no2": 33.21,
        "o3": 54.99,
        "so2": 8.77,
        "pm2_5": 27.07,
        "pm10": 31.23,
        "nh3": 0
      },
      "dt": 1760322882
    }
  ],
  "warnings": [
    {
      "type": "co",
      "value": 200.13,
      "unit": "μg/m³",
      "level": "Good"
    },
    {
      "type": "pm2_5",
      "value": 27.07,
      "unit": "μg/m³",
      "level": "Moderate"
    },
    {
      "type": "pm10",
      "value": 31.23,
      "unit": "μg/m³",
      "level": "Good"
    }
  ]
}