{
  "coord": {
    "lon": 139.6425,
    "lat": 35.4478
  },
  "list": [
    {
      "main": {
        "aqi": 3
      },
      "components": {
        "co": 181.62,
        "no": 0,
        "no2": 3.58,
        "o3": 120.27,
        "so2": 6.86,
        "pm2_5": 4.94,
        "pm10": 8.26,
        "nh3": 0.21
      },
      "dt": 1778864680
    }
  ],
  "warnings": [
    {
      "type": "co",
      "value": 181.62,
      "unit": "μg/m³",
      "level": "Good"
    },
    {
      "type": "pm2_5",
      "value": 4.94,
      "unit": "μg/m³",
      "level": "Good"
    },
    {
      "type": "pm10",
      "value": 8.26,
      "unit": "μg/m³",
      "level": "Good"
    }
  ]
}