{
  "coord": {
    "lon": 139.6425,
    "lat": 35.4478
  },
  "list": [
    {
      "main": {
        "aqi": 2
      },
      "components": {
        "co": 195.38,
        "no": 2.08,
        "no2": 33.89,
        "o3": 34.86,
        "so2": 8.1,
        "pm2_5": 22.89,
        "pm10": 26.28,
        "nh3": 0
      },
      "dt": 1760314866
    }
  ],
  "warnings": [
    {
      "type": "co",
      "value": 195.38,
      "unit": "μg/m³",
      "level": "Good"
    },
    {
      "type": "pm2_5",
      "value": 22.89,
      "unit": "μg/m³",
      "level": "Moderate"
    },
    {
      "type": "pm10",
      "value": 26.28,
      "unit": "μg/m³",
      "level": "Good"
    }
  ]
}