{
  "coord": {
    "lon": 139.6425,
    "lat": 35.4478
  },
  "list": [
    {
      "main": {
        "aqi": 2
      },
      "components": {
        "co": 170.07,
        "no": 0,
        "no2": 19.81,
        "o3": 62.64,
        "so2": 17.77,
        "pm2_5": 6.75,
        "pm10": 10.33,
        "nh3": 0.01
      },
      "dt": 1772196462
    }
  ],
  "warnings": [
    {
      "type": "co",
      "value": 170.07,
      "unit": "μg/m³",
      "level": "Good"
    },
    {
      "type": "pm2_5",
      "value": 6.75,
      "unit": "μg/m³",
      "level": "Good"
    },
    {
      "type": "pm10",
      "value": 10.33,
      "unit": "μg/m³",
      "level": "Good"
    }
  ]
}