{
  "coord": {
    "lon": 139.6425,
    "lat": 35.4478
  },
  "list": [
    {
      "main": {
        "aqi": 1
      },
      "components": {
        "co": 191.88,
        "no": 0,
        "no2": 23.98,
        "o3": 42.83,
        "so2": 2.77,
        "pm2_5": 5.08,
        "pm10": 6.16,
        "nh3": 0.01
      },
      "dt": 1766657121
    }
  ],
  "warnings": [
    {
      "type": "co",
      "value": 191.88,
      "unit": "μg/m³",
      "level": "Good"
    },
    {
      "type": "pm2_5",
      "value": 5.08,
      "unit": "μg/m³",
      "level": "Good"
    },
    {
      "type": "pm10",
      "value": 6.16,
      "unit": "μg/m³",
      "level": "Good"
    }
  ]
}