[
  {
    "No": "No1",
    "Title": "震源・震度情報",
    "EventID": "20260115193551",
    "time": "2026/01/15 19:35",
    "time_full": "2026/01/15 19:35:51",
    "location": "宗谷地方南部",
    "magnitude": "2.8",
    "depth": "0km",
    "latitude": "45.1",
    "longitude": "142.2",
    "info": "この地震による津波の心配はありません。",
    "intensity": "1"
  },
  {
    "No": "No2",
    "Title": "震源・震度情報",
    "EventID": "20260115145724",
    "time": "2026/01/15 14:57",
    "time_full": "2026/01/15 14:57:24",
    "location": "富山県東部",
    "magnitude": "3.5",
    "depth": "0km",
    "latitude": "36.4",
    "longitude": "137.6",
    "info": "",
    "intensity": "2"
  },
  {
    "No": "No3",
    "Title": "震源・震度情報",
    "EventID": "20260115145251",
    "time": "2026/01/15 14:52",
    "time_full": "2026/01/15 14:52:51",
    "location": "岐阜県飛騨地方",
    "magnitude": "2.9",
    "depth": "0km",
    "latitude": "36.3",
    "longitude": "137.6",
    "info": "",
    "intensity": "1"
  },
  {
    "No": "No4",
    "Title": "震源・震度情報",
    "EventID": "20260115144806",
    "time": "2026/01/15 14:48",
    "time_full": "2026/01/15 14:48:06",
    "location": "岐阜県飛騨地方",
    "magnitude": "5.2",
    "depth": "0km",
    "latitude": "36.3",
    "longitude": "137.6",
    "info": "",
    "intensity": "3"
  },
  {
    "No": "No5",
    "Title": "震源・震度情報",
    "EventID": "20260115144400",
    "time": "2026/01/15 14:44",
    "time_full": "2026/01/15 14:44:00",
    "location": "富山県東部",
    "magnitude": "4.3",
    "depth": "0km",
    "latitude": "36.4",
    "longitude": "137.6",
    "info": "",
    "intensity": "2"
  },
  {
    "No": "No6",
    "Title": "震源・震度情報",
    "EventID": "20260115144017",
    "time": "2026/01/15 14:40",
    "time_full": "2026/01/15 14:40:17",
    "location": "富山県東部",
    "magnitude": "4.7",
    "depth": "0km",
    "latitude": "36.4",
    "longitude": "137.6",
    "info": "",
    "intensity": "4"
  },
  {
    "No": "No7",
    "Title": "震源・震度情報",
    "EventID": "20260115131530",
    "time": "2026/01/15 13:15",
    "time_full": "2026/01/15 13:15:30",
    "location": "熊本県熊本地方",
    "magnitude": "2.2",
    "depth": "10km",
    "latitude": "32.7",
    "longitude": "130.8",
    "info": "",
    "intensity": "1"
  },
  {
    "No": "No8",
    "Title": "震源・震度情報",
    "EventID": "20260115111825",
    "time": "2026/01/15 11:18",
    "time_full": "2026/01/15 11:18:25",
    "location": "宮城県沖",
    "magnitude": "3.2",
    "depth": "40km",
    "latitude": "38.9",
    "longitude": "142.4",
    "info": "",
    "intensity": "1"
  },
  {
    "No": "No9",
    "Title": "震源・震度情報",
    "EventID": "20260115104626",
    "time": "2026/01/15 10:46",
    "time_full": "2026/01/15 10:46:26",
    "location": "トカラ列島近海",
    "magnitude": "1.9",
    "depth": "0km",
    "latitude": "29.7",
    "longitude": "129.6",
    "info": "",
    "intensity": "1"
  },
  {
    "No": "No10",
    "Title": "震源・震度情報",
    "EventID": "20260115102026",
    "time": "2026/01/15 10:20",
    "time_full": "2026/01/15 10:20:26",
    "location": "島根県東部",
    "magnitude": "3.0",
    "depth": "10km",
    "latitude": "35.3",
    "longitude": "133.2",
    "info": "",
    "intensity": "1"
  }
]