[
  {
    "time": "2026-01-01 00:00:00",
    "temp": 4.45,
    "temp_max": 6.98,
    "temp_min": 4.45,
    "humidity": 79,
    "feels_like": -0.21,
    "pressure": 1012,
    "rain_mm": 0
  },
  {
    "time": "2026-01-01 03:00:00",
    "temp": 5.58,
    "temp_max": 7.83,
    "temp_min": 5.58,
    "humidity": 66,
    "feels_like": 1.56,
    "pressure": 1012,
    "rain_mm": 0
  },
  {
    "time": "2026-01-01 06:00:00",
    "temp": 7.14,
    "temp_max": 8.49,
    "temp_min": 7.14,
    "humidity": 49,
    "feels_like": 5.03,
    "pressure": 1011,
    "rain_mm": 0
  },
  {
    "time": "2026-01-01 09:00:00",
    "temp": 8.65,
    "temp_max": 8.65,
    "temp_min": 8.65,
    "humidity": 37,
    "feels_like": 7.48,
    "pressure": 1012,
    "rain_mm": 0
  },
  {
    "time": "2026-01-01 12:00:00",
    "temp": 8.21,
    "temp_max": 8.21,
    "temp_min": 8.21,
    "humidity": 55,
    "feels_like": 6.53,
    "pressure": 1012,
    "rain_mm": 0
  },
  {
    "time": "2026-01-01 15:00:00",
    "temp": 6.69,
    "temp_max": 6.69,
    "temp_min": 6.69,
    "humidity": 41,
    "feels_like": 3.14,
    "pressure": 1011,
    "rain_mm": 0.45
  },
  {
    "time": "2026-01-01 18:00:00",
    "temp": 5.48,
    "temp_max": 5.48,
    "temp_min": 5.48,
    "humidity": 49,
    "feels_like": 1.73,
    "pressure": 1011,
    "rain_mm": 0.23
  },
  {
    "time": "2026-01-01 21:00:00",
    "temp": 5.42,
    "temp_max": 5.42,
    "temp_min": 5.42,
    "humidity": 55,
    "feels_like": 2.52,
    "pressure": 1011,
    "rain_mm": 0
  },
  {
    "time": "2026-01-02 00:00:00",
    "temp": 5.17,
    "temp_max": 5.17,
    "temp_min": 5.17,
    "humidity": 68,
    "feels_like": 2.82,
    "pressure": 1011,
    "rain_mm": 0
  },
  {
    "time": "2026-01-02 03:00:00",
    "temp": 5.17,
    "temp_max": 5.17,
    "temp_min": 5.17,
    "humidity": 83,
    "feels_like": 2.6,
    "pressure": 1008,
    "rain_mm": 0.57
  },
  {
    "time": "2026-01-02 06:00:00",
    "temp": 6.2,
    "temp_max": 6.2,
    "temp_min": 6.2,
    "humidity": 76,
    "feels_like": 3.35,
    "pressure": 1006,
    "rain_mm": 0.78
  },
  {
    "time": "2026-01-02 09:00:00",
    "temp": 8.67,
    "temp_max": 8.67,
    "temp_min": 8.67,
    "humidity": 36,
    "feels_like": 4.62,
    "pressure": 1005,
    "rain_mm": 0.89
  },
  {
    "time": "2026-01-02 12:00:00",
    "temp": 2.89,
    "temp_max": 2.89,
    "temp_min": 2.89,
    "humidity": 98,
    "feels_like": -4.11,
    "pressure": 1007,
    "rain_mm": 0
  },
  {
    "time": "2026-01-02 15:00:00",
    "temp": 3.55,
    "temp_max": 3.55,
    "temp_min": 3.55,
    "humidity": 74,
    "feels_like": -1.91,
    "pressure": 1008,
    "rain_mm": 0
  },
  {
    "time": "2026-01-02 18:00:00",
    "temp": 3.77,
    "temp_max": 3.77,
    "temp_min": 3.77,
    "humidity": 73,
    "feels_like": -0.67,
    "pressure": 1010,
    "rain_mm": 0
  },
  {
    "time": "2026-01-02 21:00:00",
    "temp": 4.33,
    "temp_max": 4.33,
    "temp_min": 4.33,
    "humidity": 45,
    "feels_like": 0.4,
    "pressure": 1011,
    "rain_mm": 0
  },
  {
    "time": "2026-01-03 00:00:00",
    "temp": 5.32,
    "temp_max": 5.32,
    "temp_min": 5.32,
    "humidity": 35,
    "feels_like": 3.07,
    "pressure": 1012,
    "rain_mm": 0
  },
  {
    "time": "2026-01-03 03:00:00",
    "temp": 7.6,
    "temp_max": 7.6,
    "temp_min": 7.6,
    "humidity": 22,
    "feels_like": 6.88,
    "pressure": 1012,
    "rain_mm": 0
  },
  {
    "time": "2026-01-03 06:00:00",
    "temp": 8.46,
    "temp_max": 8.46,
    "temp_min": 8.46,
    "humidity": 21,
    "feels_like": 7.73,
    "pressure": 1012,
    "rain_mm": 0
  },
  {
    "time": "2026-01-03 09:00:00",
    "temp": 9.03,
    "temp_max": 9.03,
    "temp_min": 9.03,
    "humidity": 24,
    "feels_like": 9.03,
    "pressure": 1013,
    "rain_mm": 0
  },
  {
    "time": "2026-01-03 12:00:00",
    "temp": 8.64,
    "temp_max": 8.64,
    "temp_min": 8.64,
    "humidity": 28,
    "feels_like": 7.11,
    "pressure": 1015,
    "rain_mm": 0
  },
  {
    "time": "2026-01-03 15:00:00",
    "temp": 7.17,
    "temp_max": 7.17,
    "temp_min": 7.17,
    "humidity": 42,
    "feels_like": 4.45,
    "pressure": 1015,
    "rain_mm": 0
  },
  {
    "time": "2026-01-03 18:00:00",
    "temp": 6.33,
    "temp_max": 6.33,
    "temp_min": 6.33,
    "humidity": 40,
    "feels_like": 6.33,
    "pressure": 1016,
    "rain_mm": 0
  },
  {
    "time": "2026-01-03 21:00:00",
    "temp": 6.11,
    "temp_max": 6.11,
    "temp_min": 6.11,
    "humidity": 41,
    "feels_like": 6.11,
    "pressure": 1016,
    "rain_mm": 0
  },
  {
    "time": "2026-01-04 00:00:00",
    "temp": 6.34,
    "temp_max": 6.34,
    "temp_min": 6.34,
    "humidity": 43,
    "feels_like": 4.66,
    "pressure": 1017,
    "rain_mm": 0
  },
  {
    "time": "2026-01-04 03:00:00",
    "temp": 8.18,
    "temp_max": 8.18,
    "temp_min": 8.18,
    "humidity": 41,
    "feels_like": 8.18,
    "pressure": 1014,
    "rain_mm": 0
  },
  {
    "time": "2026-01-04 06:00:00",
    "temp": 9.72,
    "temp_max": 9.72,
    "temp_min": 9.72,
    "humidity": 37,
    "feels_like": 8.72,
    "pressure": 1013,
    "rain_mm": 0
  },
  {
    "time": "2026-01-04 09:00:00",
    "temp": 10.19,
    "temp_max": 10.19,
    "temp_min": 10.19,
    "humidity": 36,
    "feels_like": 8.2,
    "pressure": 1014,
    "rain_mm": 0
  },
  {
    "time": "2026-01-04 12:00:00",
    "temp": 9.82,
    "temp_max": 9.82,
    "temp_min": 9.82,
    "humidity": 39,
    "feels_like": 9.82,
    "pressure": 1014,
    "rain_mm": 0
  },
  {
    "time": "2026-01-04 15:00:00",
    "temp": 8.6,
    "temp_max": 8.6,
    "temp_min": 8.6,
    "humidity": 43,
    "feels_like": 6.83,
    "pressure": 1012,
    "rain_mm": 0
  },
  {
    "time": "2026-01-04 18:00:00",
    "temp": 7.68,
    "temp_max": 7.68,
    "temp_min": 7.68,
    "humidity": 50,
    "feels_like": 6.95,
    "pressure": 1011,
    "rain_mm": 0
  },
  {
    "time": "2026-01-04 21:00:00",
    "temp": 6.85,
    "temp_max": 6.85,
    "temp_min": 6.85,
    "humidity": 56,
    "feels_like": 4.66,
    "pressure": 1009,
    "rain_mm": 0
  },
  {
    "time": "2026-01-05 00:00:00",
    "temp": 7.05,
    "temp_max": 7.05,
    "temp_min": 7.05,
    "humidity": 55,
    "feels_like": 5.18,
    "pressure": 1007,
    "rain_mm": 0
  },
  {
    "time": "2026-01-05 03:00:00",
    "temp": 10.16,
    "temp_max": 10.16,
    "temp_min": 10.16,
    "humidity": 44,
    "feels_like": 8.38,
    "pressure": 1005,
    "rain_mm": 0
  },
  {
    "time": "2026-01-05 06:00:00",
    "temp": 13.08,
    "temp_max": 13.08,
    "temp_min": 13.08,
    "humidity": 34,
    "feels_like": 11.33,
    "pressure": 1006,
    "rain_mm": 0
  },
  {
    "time": "2026-01-05 09:00:00",
    "temp": 9.08,
    "temp_max": 9.08,
    "temp_min": 9.08,
    "humidity": 38,
    "feels_like": 4.8,
    "pressure": 1009,
    "rain_mm": 0
  },
  {
    "time": "2026-01-05 12:00:00",
    "temp": 7.5,
    "temp_max": 7.5,
    "temp_min": 7.5,
    "humidity": 39,
    "feels_like": 3.12,
    "pressure": 1012,
    "rain_mm": 0
  },
  {
    "time": "2026-01-05 15:00:00",
    "temp": 6.49,
    "temp_max": 6.49,
    "temp_min": 6.49,
    "humidity": 44,
    "feels_like": 2.29,
    "pressure": 1013,
    "rain_mm": 0
  },
  {
    "time": "2026-01-05 18:00:00",
    "temp": 5.7,
    "temp_max": 5.7,
    "temp_min": 5.7,
    "humidity": 45,
    "feels_like": 1.55,
    "pressure": 1014,
    "rain_mm": 0
  },
  {
    "time": "2026-01-05 21:00:00",
    "temp": 5.21,
    "temp_max": 5.21,
    "temp_min": 5.21,
    "humidity": 45,
    "feels_like": 2.04,
    "pressure": 1016,
    "rain_mm": 0
  }
]