[
  {
    "time": "2025-10-19 06:00:00",
    "temp": 21.88,
    "temp_max": 21.88,
    "temp_min": 21.05,
    "humidity": 80,
    "feels_like": 22.21,
    "pressure": 1020,
    "rain_mm": 0
  },
  {
    "time": "2025-10-19 09:00:00",
    "temp": 21.33,
    "temp_max": 21.33,
    "temp_min": 20.22,
    "humidity": 77,
    "feels_like": 21.53,
    "pressure": 1021,
    "rain_mm": 0.16
  },
  {
    "time": "2025-10-19 12:00:00",
    "temp": 20.12,
    "temp_max": 20.12,
    "temp_min": 19.24,
    "humidity": 76,
    "feels_like": 20.17,
    "pressure": 1021,
    "rain_mm": 0.24
  },
  {
    "time": "2025-10-19 15:00:00",
    "temp": 17.8,
    "temp_max": 17.8,
    "temp_min": 17.8,
    "humidity": 82,
    "feels_like": 17.78,
    "pressure": 1020,
    "rain_mm": 3.25
  },
  {
    "time": "2025-10-19 18:00:00",
    "temp": 16.92,
    "temp_max": 16.92,
    "temp_min": 16.92,
    "humidity": 88,
    "feels_like": 16.97,
    "pressure": 1018,
    "rain_mm": 11.36
  },
  {
    "time": "2025-10-19 21:00:00",
    "temp": 17.68,
    "temp_max": 17.68,
    "temp_min": 17.68,
    "humidity": 84,
    "feels_like": 17.7,
    "pressure": 1018,
    "rain_mm": 0.76
  },
  {
    "time": "2025-10-20 00:00:00",
    "temp": 18.25,
    "temp_max": 18.25,
    "temp_min": 18.25,
    "humidity": 79,
    "feels_like": 18.19,
    "pressure": 1019,
    "rain_mm": 0.14
  },
  {
    "time": "2025-10-20 03:00:00",
    "temp": 20.01,
    "temp_max": 20.01,
    "temp_min": 20.01,
    "humidity": 72,
    "feels_like": 19.95,
    "pressure": 1017,
    "rain_mm": 0
  },
  {
    "time": "2025-10-20 06:00:00",
    "temp": 20.73,
    "temp_max": 20.73,
    "temp_min": 20.73,
    "humidity": 73,
    "feels_like": 20.76,
    "pressure": 1017,
    "rain_mm": 0
  },
  {
    "time": "2025-10-20 09:00:00",
    "temp": 21.01,
    "temp_max": 21.01,
    "temp_min": 21.01,
    "humidity": 76,
    "feels_like": 21.15,
    "pressure": 1019,
    "rain_mm": 0
  },
  {
    "time": "2025-10-20 12:00:00",
    "temp": 20.43,
    "temp_max": 20.43,
    "temp_min": 20.43,
    "humidity": 80,
    "feels_like": 20.62,
    "pressure": 1020,
    "rain_mm": 0.18
  },
  {
    "time": "2025-10-20 15:00:00",
    "temp": 17.73,
    "temp_max": 17.73,
    "temp_min": 17.73,
    "humidity": 81,
    "feels_like": 17.67,
    "pressure": 1022,
    "rain_mm": 2.18
  },
  {
    "time": "2025-10-20 18:00:00",
    "temp": 16.24,
    "temp_max": 16.24,
    "temp_min": 16.24,
    "humidity": 71,
    "feels_like": 15.77,
    "pressure": 1023,
    "rain_mm": 0.84
  },
  {
    "time": "2025-10-20 21:00:00",
    "temp": 15.84,
    "temp_max": 15.84,
    "temp_min": 15.84,
    "humidity": 72,
    "feels_like": 15.36,
    "pressure": 1025,
    "rain_mm": 0.53
  },
  {
    "time": "2025-10-21 00:00:00",
    "temp": 15.74,
    "temp_max": 15.74,
    "temp_min": 15.74,
    "humidity": 67,
    "feels_like": 15.12,
    "pressure": 1026,
    "rain_mm": 0.2
  },
  {
    "time": "2025-10-21 03:00:00",
    "temp": 14.74,
    "temp_max": 14.74,
    "temp_min": 14.74,
    "humidity": 74,
    "feels_like": 14.2,
    "pressure": 1025,
    "rain_mm": 1.06
  },
  {
    "time": "2025-10-21 06:00:00",
    "temp": 14.95,
    "temp_max": 14.95,
    "temp_min": 14.95,
    "humidity": 75,
    "feels_like": 14.46,
    "pressure": 1025,
    "rain_mm": 1.07
  },
  {
    "time": "2025-10-21 09:00:00",
    "temp": 15.55,
    "temp_max": 15.55,
    "temp_min": 15.55,
    "humidity": 69,
    "feels_like": 14.96,
    "pressure": 1026,
    "rain_mm": 0.27
  },
  {
    "time": "2025-10-21 12:00:00",
    "temp": 15.21,
    "temp_max": 15.21,
    "temp_min": 15.21,
    "humidity": 73,
    "feels_like": 14.69,
    "pressure": 1026,
    "rain_mm": 0.38
  },
  {
    "time": "2025-10-21 15:00:00",
    "temp": 14.83,
    "temp_max": 14.83,
    "temp_min": 14.83,
    "humidity": 79,
    "feels_like": 14.43,
    "pressure": 1025,
    "rain_mm": 2.49
  },
  {
    "time": "2025-10-21 18:00:00",
    "temp": 14.07,
    "temp_max": 14.07,
    "temp_min": 14.07,
    "humidity": 80,
    "feels_like": 13.62,
    "pressure": 1024,
    "rain_mm": 3.71
  },
  {
    "time": "2025-10-21 21:00:00",
    "temp": 14.05,
    "temp_max": 14.05,
    "temp_min": 14.05,
    "humidity": 83,
    "feels_like": 13.68,
    "pressure": 1025,
    "rain_mm": 3.78
  },
  {
    "time": "2025-10-22 00:00:00",
    "temp": 14.2,
    "temp_max": 14.2,
    "temp_min": 14.2,
    "humidity": 77,
    "feels_like": 13.69,
    "pressure": 1026,
    "rain_mm": 1.69
  },
  {
    "time": "2025-10-22 03:00:00",
    "temp": 14.48,
    "temp_max": 14.48,
    "temp_min": 14.48,
    "humidity": 73,
    "feels_like": 13.89,
    "pressure": 1025,
    "rain_mm": 3.04
  },
  {
    "time": "2025-10-22 06:00:00",
    "temp": 15.99,
    "temp_max": 15.99,
    "temp_min": 15.99,
    "humidity": 57,
    "feels_like": 15.13,
    "pressure": 1025,
    "rain_mm": 0
  },
  {
    "time": "2025-10-22 09:00:00",
    "temp": 16.29,
    "temp_max": 16.29,
    "temp_min": 16.29,
    "humidity": 59,
    "feels_like": 15.52,
    "pressure": 1026,
    "rain_mm": 0
  },
  {
    "time": "2025-10-22 12:00:00",
    "temp": 16.5,
    "temp_max": 16.5,
    "temp_min": 16.5,
    "humidity": 56,
    "feels_like": 15.67,
    "pressure": 1027,
    "rain_mm": 0
  },
  {
    "time": "2025-10-22 15:00:00",
    "temp": 16.31,
    "temp_max": 16.31,
    "temp_min": 16.31,
    "humidity": 54,
    "feels_like": 15.41,
    "pressure": 1026,
    "rain_mm": 0
  },
  {
    "time": "2025-10-22 18:00:00",
    "temp": 15.94,
    "temp_max": 15.94,
    "temp_min": 15.94,
    "humidity": 51,
    "feels_like": 14.92,
    "pressure": 1026,
    "rain_mm": 0
  },
  {
    "time": "2025-10-22 21:00:00",
    "temp": 15.71,
    "temp_max": 15.71,
    "temp_min": 15.71,
    "humidity": 52,
    "feels_like": 14.69,
    "pressure": 1026,
    "rain_mm": 0
  },
  {
    "time": "2025-10-23 00:00:00",
    "temp": 16.52,
    "temp_max": 16.52,
    "temp_min": 16.52,
    "humidity": 52,
    "feels_like": 15.59,
    "pressure": 1027,
    "rain_mm": 0
  },
  {
    "time": "2025-10-23 03:00:00",
    "temp": 17.62,
    "temp_max": 17.62,
    "temp_min": 17.62,
    "humidity": 47,
    "feels_like": 16.66,
    "pressure": 1027,
    "rain_mm": 0
  },
  {
    "time": "2025-10-23 06:00:00",
    "temp": 18.46,
    "temp_max": 18.46,
    "temp_min": 18.46,
    "humidity": 47,
    "feels_like": 17.59,
    "pressure": 1026,
    "rain_mm": 0
  },
  {
    "time": "2025-10-23 09:00:00",
    "temp": 17.55,
    "temp_max": 17.55,
    "temp_min": 17.55,
    "humidity": 54,
    "feels_like": 16.77,
    "pressure": 1027,
    "rain_mm": 0
  },
  {
    "time": "2025-10-23 12:00:00",
    "temp": 17.03,
    "temp_max": 17.03,
    "temp_min": 17.03,
    "humidity": 54,
    "feels_like": 16.2,
    "pressure": 1028,
    "rain_mm": 0
  },
  {
    "time": "2025-10-23 15:00:00",
    "temp": 16.79,
    "temp_max": 16.79,
    "temp_min": 16.79,
    "humidity": 55,
    "feels_like": 15.96,
    "pressure": 1027,
    "rain_mm": 0
  },
  {
    "time": "2025-10-23 18:00:00",
    "temp": 15.96,
    "temp_max": 15.96,
    "temp_min": 15.96,
    "humidity": 57,
    "feels_like": 15.1,
    "pressure": 1027,
    "rain_mm": 0
  },
  {
    "time": "2025-10-23 21:00:00",
    "temp": 15.43,
    "temp_max": 15.43,
    "temp_min": 15.43,
    "humidity": 59,
    "feels_like": 14.57,
    "pressure": 1027,
    "rain_mm": 0
  },
  {
    "time": "2025-10-24 00:00:00",
    "temp": 16.36,
    "temp_max": 16.36,
    "temp_min": 16.36,
    "humidity": 53,
    "feels_like": 15.44,
    "pressure": 1028,
    "rain_mm": 0
  },
  {
    "time": "2025-10-24 03:00:00",
    "temp": 18.05,
    "temp_max": 18.05,
    "temp_min": 18.05,
    "humidity": 45,
    "feels_like": 17.09,
    "pressure": 1027,
    "rain_mm": 0
  }
]