[
  {
    "time": "2026-01-11 06:00:00",
    "temp": 12.6,
    "temp_max": 12.6,
    "temp_min": 9.91,
    "humidity": 20,
    "feels_like": 10.44,
    "pressure": 1000,
    "rain_mm": 0
  },
  {
    "time": "2026-01-11 09:00:00",
    "temp": 10.7,
    "temp_max": 10.7,
    "temp_min": 6.89,
    "humidity": 24,
    "feels_like": 8.45,
    "pressure": 1002,
    "rain_mm": 0
  },
  {
    "time": "2026-01-11 12:00:00",
    "temp": 7.97,
    "temp_max": 7.97,
    "temp_min": 5.66,
    "humidity": 28,
    "feels_like": 3.3,
    "pressure": 1005,
    "rain_mm": 0
  },
  {
    "time": "2026-01-11 15:00:00",
    "temp": 4.98,
    "temp_max": 4.98,
    "temp_min": 4.98,
    "humidity": 30,
    "feels_like": 1.21,
    "pressure": 1010,
    "rain_mm": 0
  },
  {
    "time": "2026-01-11 18:00:00",
    "temp": 4.48,
    "temp_max": 4.48,
    "temp_min": 4.48,
    "humidity": 32,
    "feels_like": 0.26,
    "pressure": 1012,
    "rain_mm": 0
  },
  {
    "time": "2026-01-11 21:00:00",
    "temp": 4.43,
    "temp_max": 4.43,
    "temp_min": 4.43,
    "humidity": 30,
    "feels_like": 3.02,
    "pressure": 1014,
    "rain_mm": 0
  },
  {
    "time": "2026-01-12 00:00:00",
    "temp": 4.8,
    "temp_max": 4.8,
    "temp_min": 4.8,
    "humidity": 30,
    "feels_like": 3.06,
    "pressure": 1016,
    "rain_mm": 0
  },
  {
    "time": "2026-01-12 03:00:00",
    "temp": 5.98,
    "temp_max": 5.98,
    "temp_min": 5.98,
    "humidity": 35,
    "feels_like": 4.08,
    "pressure": 1016,
    "rain_mm": 0
  },
  {
    "time": "2026-01-12 06:00:00",
    "temp": 7.08,
    "temp_max": 7.08,
    "temp_min": 7.08,
    "humidity": 43,
    "feels_like": 4.11,
    "pressure": 1016,
    "rain_mm": 0
  },
  {
    "time": "2026-01-12 09:00:00",
    "temp": 8.01,
    "temp_max": 8.01,
    "temp_min": 8.01,
    "humidity": 43,
    "feels_like": 5.45,
    "pressure": 1016,
    "rain_mm": 0
  },
  {
    "time": "2026-01-12 12:00:00",
    "temp": 8.12,
    "temp_max": 8.12,
    "temp_min": 8.12,
    "humidity": 43,
    "feels_like": 6.18,
    "pressure": 1015,
    "rain_mm": 0
  },
  {
    "time": "2026-01-12 15:00:00",
    "temp": 7.06,
    "temp_max": 7.06,
    "temp_min": 7.06,
    "humidity": 48,
    "feels_like": 3.81,
    "pressure": 1013,
    "rain_mm": 0
  },
  {
    "time": "2026-01-12 18:00:00",
    "temp": 5.82,
    "temp_max": 5.82,
    "temp_min": 5.82,
    "humidity": 46,
    "feels_like": 3.6,
    "pressure": 1012,
    "rain_mm": 0
  },
  {
    "time": "2026-01-12 21:00:00",
    "temp": 6.93,
    "temp_max": 6.93,
    "temp_min": 6.93,
    "humidity": 54,
    "feels_like": 2.93,
    "pressure": 1011,
    "rain_mm": 0
  },
  {
    "time": "2026-01-13 00:00:00",
    "temp": 11.11,
    "temp_max": 11.11,
    "temp_min": 11.11,
    "humidity": 47,
    "feels_like": 9.5,
    "pressure": 1009,
    "rain_mm": 0
  },
  {
    "time": "2026-01-13 03:00:00",
    "temp": 13.87,
    "temp_max": 13.87,
    "temp_min": 13.87,
    "humidity": 42,
    "feels_like": 12.41,
    "pressure": 1006,
    "rain_mm": 0
  },
  {
    "time": "2026-01-13 06:00:00",
    "temp": 13.84,
    "temp_max": 13.84,
    "temp_min": 13.84,
    "humidity": 44,
    "feels_like": 12.43,
    "pressure": 1005,
    "rain_mm": 0
  },
  {
    "time": "2026-01-13 09:00:00",
    "temp": 13.48,
    "temp_max": 13.48,
    "temp_min": 13.48,
    "humidity": 44,
    "feels_like": 12.03,
    "pressure": 1006,
    "rain_mm": 0
  },
  {
    "time": "2026-01-13 12:00:00",
    "temp": 12.24,
    "temp_max": 12.24,
    "temp_min": 12.24,
    "humidity": 41,
    "feels_like": 10.59,
    "pressure": 1006,
    "rain_mm": 0
  },
  {
    "time": "2026-01-13 15:00:00",
    "temp": 10.83,
    "temp_max": 10.83,
    "temp_min": 10.83,
    "humidity": 38,
    "feels_like": 8.96,
    "pressure": 1007,
    "rain_mm": 0
  },
  {
    "time": "2026-01-13 18:00:00",
    "temp": 8.68,
    "temp_max": 8.68,
    "temp_min": 8.68,
    "humidity": 40,
    "feels_like": 5.69,
    "pressure": 1009,
    "rain_mm": 0
  },
  {
    "time": "2026-01-13 21:00:00",
    "temp": 7.45,
    "temp_max": 7.45,
    "temp_min": 7.45,
    "humidity": 46,
    "feels_like": 4.02,
    "pressure": 1012,
    "rain_mm": 0
  },
  {
    "time": "2026-01-14 00:00:00",
    "temp": 7.29,
    "temp_max": 7.29,
    "temp_min": 7.29,
    "humidity": 45,
    "feels_like": 4.06,
    "pressure": 1014,
    "rain_mm": 0
  },
  {
    "time": "2026-01-14 03:00:00",
    "temp": 9.16,
    "temp_max": 9.16,
    "temp_min": 9.16,
    "humidity": 37,
    "feels_like": 7.97,
    "pressure": 1015,
    "rain_mm": 0
  },
  {
    "time": "2026-01-14 06:00:00",
    "temp": 10.23,
    "temp_max": 10.23,
    "temp_min": 10.23,
    "humidity": 32,
    "feels_like": 8.14,
    "pressure": 1016,
    "rain_mm": 0
  },
  {
    "time": "2026-01-14 09:00:00",
    "temp": 10.5,
    "temp_max": 10.5,
    "temp_min": 10.5,
    "humidity": 32,
    "feels_like": 8.44,
    "pressure": 1019,
    "rain_mm": 0
  },
  {
    "time": "2026-01-14 12:00:00",
    "temp": 9.39,
    "temp_max": 9.39,
    "temp_min": 9.39,
    "humidity": 31,
    "feels_like": 7.43,
    "pressure": 1021,
    "rain_mm": 0
  },
  {
    "time": "2026-01-14 15:00:00",
    "temp": 8.18,
    "temp_max": 8.18,
    "temp_min": 8.18,
    "humidity": 37,
    "feels_like": 5.7,
    "pressure": 1021,
    "rain_mm": 0
  },
  {
    "time": "2026-01-14 18:00:00",
    "temp": 7,
    "temp_max": 7,
    "temp_min": 7,
    "humidity": 44,
    "feels_like": 4.28,
    "pressure": 1020,
    "rain_mm": 0
  },
  {
    "time": "2026-01-14 21:00:00",
    "temp": 6.68,
    "temp_max": 6.68,
    "temp_min": 6.68,
    "humidity": 45,
    "feels_like": 3.89,
    "pressure": 1021,
    "rain_mm": 0
  },
  {
    "time": "2026-01-15 00:00:00",
    "temp": 6.7,
    "temp_max": 6.7,
    "temp_min": 6.7,
    "humidity": 43,
    "feels_like": 4.91,
    "pressure": 1021,
    "rain_mm": 0
  },
  {
    "time": "2026-01-15 03:00:00",
    "temp": 7.99,
    "temp_max": 7.99,
    "temp_min": 7.99,
    "humidity": 46,
    "feels_like": 6.91,
    "pressure": 1018,
    "rain_mm": 0
  },
  {
    "time": "2026-01-15 06:00:00",
    "temp": 10.14,
    "temp_max": 10.14,
    "temp_min": 10.14,
    "humidity": 53,
    "feels_like": 8.59,
    "pressure": 1015,
    "rain_mm": 0
  },
  {
    "time": "2026-01-15 09:00:00",
    "temp": 12.34,
    "temp_max": 12.34,
    "temp_min": 12.34,
    "humidity": 39,
    "feels_like": 10.65,
    "pressure": 1013,
    "rain_mm": 0
  },
  {
    "time": "2026-01-15 12:00:00",
    "temp": 11.78,
    "temp_max": 11.78,
    "temp_min": 11.78,
    "humidity": 42,
    "feels_like": 10.11,
    "pressure": 1012,
    "rain_mm": 0
  },
  {
    "time": "2026-01-15 15:00:00",
    "temp": 11.06,
    "temp_max": 11.06,
    "temp_min": 11.06,
    "humidity": 47,
    "feels_like": 9.45,
    "pressure": 1011,
    "rain_mm": 0
  },
  {
    "time": "2026-01-15 18:00:00",
    "temp": 9.74,
    "temp_max": 9.74,
    "temp_min": 9.74,
    "humidity": 48,
    "feels_like": 8.46,
    "pressure": 1011,
    "rain_mm": 0
  },
  {
    "time": "2026-01-15 21:00:00",
    "temp": 9.03,
    "temp_max": 9.03,
    "temp_min": 9.03,
    "humidity": 51,
    "feels_like": 7.83,
    "pressure": 1012,
    "rain_mm": 0
  },
  {
    "time": "2026-01-16 00:00:00",
    "temp": 10.08,
    "temp_max": 10.08,
    "temp_min": 10.08,
    "humidity": 50,
    "feels_like": 8.45,
    "pressure": 1014,
    "rain_mm": 0
  },
  {
    "time": "2026-01-16 03:00:00",
    "temp": 12.66,
    "temp_max": 12.66,
    "temp_min": 12.66,
    "humidity": 45,
    "feels_like": 11.16,
    "pressure": 1013,
    "rain_mm": 0
  }
]