[
  {
    "time": "2026-05-13 15:00:00",
    "temp": 19.16,
    "temp_max": 19.31,
    "temp_min": 19.16,
    "humidity": 75,
    "feels_like": 19.09,
    "pressure": 1009,
    "rain_mm": 0
  },
  {
    "time": "2026-05-13 18:00:00",
    "temp": 19.04,
    "temp_max": 19.04,
    "temp_min": 19.01,
    "humidity": 73,
    "feels_like": 18.91,
    "pressure": 1009,
    "rain_mm": 0.12
  },
  {
    "time": "2026-05-13 21:00:00",
    "temp": 18.8,
    "temp_max": 18.8,
    "temp_min": 18.8,
    "humidity": 73,
    "feels_like": 18.64,
    "pressure": 1011,
    "rain_mm": 0.24
  },
  {
    "time": "2026-05-14 00:00:00",
    "temp": 19.98,
    "temp_max": 19.98,
    "temp_min": 19.98,
    "humidity": 63,
    "feels_like": 19.68,
    "pressure": 1013,
    "rain_mm": 0.36
  },
  {
    "time": "2026-05-14 03:00:00",
    "temp": 21.42,
    "temp_max": 21.42,
    "temp_min": 21.42,
    "humidity": 55,
    "feels_like": 21.05,
    "pressure": 1013,
    "rain_mm": 0
  },
  {
    "time": "2026-05-14 06:00:00",
    "temp": 21.4,
    "temp_max": 21.4,
    "temp_min": 21.4,
    "humidity": 61,
    "feels_like": 21.19,
    "pressure": 1013,
    "rain_mm": 0.18
  },
  {
    "time": "2026-05-14 09:00:00",
    "temp": 19.94,
    "temp_max": 19.94,
    "temp_min": 19.94,
    "humidity": 68,
    "feels_like": 19.77,
    "pressure": 1016,
    "rain_mm": 0.42
  },
  {
    "time": "2026-05-14 12:00:00",
    "temp": 16.94,
    "temp_max": 16.94,
    "temp_min": 16.94,
    "humidity": 75,
    "feels_like": 16.65,
    "pressure": 1019,
    "rain_mm": 0.22
  },
  {
    "time": "2026-05-14 15:00:00",
    "temp": 15.97,
    "temp_max": 15.97,
    "temp_min": 15.97,
    "humidity": 84,
    "feels_like": 15.82,
    "pressure": 1020,
    "rain_mm": 3.19
  },
  {
    "time": "2026-05-14 18:00:00",
    "temp": 15.85,
    "temp_max": 15.85,
    "temp_min": 15.85,
    "humidity": 76,
    "feels_like": 15.48,
    "pressure": 1020,
    "rain_mm": 0.6
  },
  {
    "time": "2026-05-14 21:00:00",
    "temp": 15.57,
    "temp_max": 15.57,
    "temp_min": 15.57,
    "humidity": 76,
    "feels_like": 15.17,
    "pressure": 1022,
    "rain_mm": 0
  },
  {
    "time": "2026-05-15 00:00:00",
    "temp": 16.93,
    "temp_max": 16.93,
    "temp_min": 16.93,
    "humidity": 69,
    "feels_like": 16.48,
    "pressure": 1023,
    "rain_mm": 0
  },
  {
    "time": "2026-05-15 03:00:00",
    "temp": 19.17,
    "temp_max": 19.17,
    "temp_min": 19.17,
    "humidity": 61,
    "feels_like": 18.74,
    "pressure": 1023,
    "rain_mm": 0
  },
  {
    "time": "2026-05-15 06:00:00",
    "temp": 20.59,
    "temp_max": 20.59,
    "temp_min": 20.59,
    "humidity": 56,
    "feels_like": 20.17,
    "pressure": 1021,
    "rain_mm": 0
  },
  {
    "time": "2026-05-15 09:00:00",
    "temp": 19.91,
    "temp_max": 19.91,
    "temp_min": 19.91,
    "humidity": 64,
    "feels_like": 19.63,
    "pressure": 1023,
    "rain_mm": 0
  },
  {
    "time": "2026-05-15 12:00:00",
    "temp": 18.28,
    "temp_max": 18.28,
    "temp_min": 18.28,
    "humidity": 71,
    "feels_like": 18.02,
    "pressure": 1025,
    "rain_mm": 0
  },
  {
    "time": "2026-05-15 15:00:00",
    "temp": 17.86,
    "temp_max": 17.86,
    "temp_min": 17.86,
    "humidity": 69,
    "feels_like": 17.5,
    "pressure": 1025,
    "rain_mm": 0
  },
  {
    "time": "2026-05-15 18:00:00",
    "temp": 17.47,
    "temp_max": 17.47,
    "temp_min": 17.47,
    "humidity": 70,
    "feels_like": 17.1,
    "pressure": 1024,
    "rain_mm": 0
  },
  {
    "time": "2026-05-15 21:00:00",
    "temp": 17.53,
    "temp_max": 17.53,
    "temp_min": 17.53,
    "humidity": 69,
    "feels_like": 17.14,
    "pressure": 1024,
    "rain_mm": 0
  },
  {
    "time": "2026-05-16 00:00:00",
    "temp": 19.3,
    "temp_max": 19.3,
    "temp_min": 19.3,
    "humidity": 52,
    "feels_like": 18.64,
    "pressure": 1024,
    "rain_mm": 0
  },
  {
    "time": "2026-05-16 03:00:00",
    "temp": 20.57,
    "temp_max": 20.57,
    "temp_min": 20.57,
    "humidity": 47,
    "feels_like": 19.91,
    "pressure": 1023,
    "rain_mm": 0
  },
  {
    "time": "2026-05-16 06:00:00",
    "temp": 21.55,
    "temp_max": 21.55,
    "temp_min": 21.55,
    "humidity": 60,
    "feels_like": 21.33,
    "pressure": 1021,
    "rain_mm": 0
  },
  {
    "time": "2026-05-16 09:00:00",
    "temp": 20.35,
    "temp_max": 20.35,
    "temp_min": 20.35,
    "humidity": 73,
    "feels_like": 20.35,
    "pressure": 1020,
    "rain_mm": 0
  },
  {
    "time": "2026-05-16 12:00:00",
    "temp": 19.61,
    "temp_max": 19.61,
    "temp_min": 19.61,
    "humidity": 76,
    "feels_like": 19.61,
    "pressure": 1021,
    "rain_mm": 0
  },
  {
    "time": "2026-05-16 15:00:00",
    "temp": 19.15,
    "temp_max": 19.15,
    "temp_min": 19.15,
    "humidity": 78,
    "feels_like": 19.16,
    "pressure": 1019,
    "rain_mm": 0
  },
  {
    "time": "2026-05-16 18:00:00",
    "temp": 18.69,
    "temp_max": 18.69,
    "temp_min": 18.69,
    "humidity": 77,
    "feels_like": 18.63,
    "pressure": 1019,
    "rain_mm": 0
  },
  {
    "time": "2026-05-16 21:00:00",
    "temp": 18.75,
    "temp_max": 18.75,
    "temp_min": 18.75,
    "humidity": 63,
    "feels_like": 18.33,
    "pressure": 1019,
    "rain_mm": 0
  },
  {
    "time": "2026-05-17 00:00:00",
    "temp": 20.65,
    "temp_max": 20.65,
    "temp_min": 20.65,
    "humidity": 60,
    "feels_like": 20.34,
    "pressure": 1019,
    "rain_mm": 0
  },
  {
    "time": "2026-05-17 03:00:00",
    "temp": 21.75,
    "temp_max": 21.75,
    "temp_min": 21.75,
    "humidity": 58,
    "feels_like": 21.5,
    "pressure": 1018,
    "rain_mm": 0
  },
  {
    "time": "2026-05-17 06:00:00",
    "temp": 22.16,
    "temp_max": 22.16,
    "temp_min": 22.16,
    "humidity": 57,
    "feels_like": 21.92,
    "pressure": 1017,
    "rain_mm": 0
  },
  {
    "time": "2026-05-17 09:00:00",
    "temp": 20.49,
    "temp_max": 20.49,
    "temp_min": 20.49,
    "humidity": 64,
    "feels_like": 20.27,
    "pressure": 1017,
    "rain_mm": 0
  },
  {
    "time": "2026-05-17 12:00:00",
    "temp": 20.05,
    "temp_max": 20.05,
    "temp_min": 20.05,
    "humidity": 67,
    "feels_like": 19.86,
    "pressure": 1018,
    "rain_mm": 0
  },
  {
    "time": "2026-05-17 15:00:00",
    "temp": 19.63,
    "temp_max": 19.63,
    "temp_min": 19.63,
    "humidity": 68,
    "feels_like": 19.42,
    "pressure": 1018,
    "rain_mm": 0
  },
  {
    "time": "2026-05-17 18:00:00",
    "temp": 19.15,
    "temp_max": 19.15,
    "temp_min": 19.15,
    "humidity": 70,
    "feels_like": 18.95,
    "pressure": 1018,
    "rain_mm": 0
  },
  {
    "time": "2026-05-17 21:00:00",
    "temp": 19,
    "temp_max": 19,
    "temp_min": 19,
    "humidity": 69,
    "feels_like": 18.76,
    "pressure": 1018,
    "rain_mm": 0
  },
  {
    "time": "2026-05-18 00:00:00",
    "temp": 20.36,
    "temp_max": 20.36,
    "temp_min": 20.36,
    "humidity": 62,
    "feels_like": 20.07,
    "pressure": 1018,
    "rain_mm": 0
  },
  {
    "time": "2026-05-18 03:00:00",
    "temp": 22,
    "temp_max": 22,
    "temp_min": 22,
    "humidity": 56,
    "feels_like": 21.72,
    "pressure": 1017,
    "rain_mm": 0
  },
  {
    "time": "2026-05-18 06:00:00",
    "temp": 22.07,
    "temp_max": 22.07,
    "temp_min": 22.07,
    "humidity": 59,
    "feels_like": 21.87,
    "pressure": 1015,
    "rain_mm": 0
  },
  {
    "time": "2026-05-18 09:00:00",
    "temp": 20.76,
    "temp_max": 20.76,
    "temp_min": 20.76,
    "humidity": 68,
    "feels_like": 20.67,
    "pressure": 1015,
    "rain_mm": 0
  },
  {
    "time": "2026-05-18 12:00:00",
    "temp": 20.23,
    "temp_max": 20.23,
    "temp_min": 20.23,
    "humidity": 74,
    "feels_like": 20.24,
    "pressure": 1016,
    "rain_mm": 0
  }
]