[
  {
    "time": "2026-01-28 06:00:00",
    "temp": 7.94,
    "temp_max": 7.94,
    "temp_min": 7.48,
    "humidity": 39,
    "feels_like": 5.36,
    "pressure": 1015,
    "rain_mm": 0
  },
  {
    "time": "2026-01-28 09:00:00",
    "temp": 7.68,
    "temp_max": 7.68,
    "temp_min": 7.15,
    "humidity": 45,
    "feels_like": 5.43,
    "pressure": 1015,
    "rain_mm": 0
  },
  {
    "time": "2026-01-28 12:00:00",
    "temp": 6.63,
    "temp_max": 6.63,
    "temp_min": 5.98,
    "humidity": 66,
    "feels_like": 4.1,
    "pressure": 1016,
    "rain_mm": 0.35
  },
  {
    "time": "2026-01-28 15:00:00",
    "temp": 5.37,
    "temp_max": 5.37,
    "temp_min": 5.37,
    "humidity": 48,
    "feels_like": 1.29,
    "pressure": 1017,
    "rain_mm": 1.22
  },
  {
    "time": "2026-01-28 18:00:00",
    "temp": 4.81,
    "temp_max": 4.81,
    "temp_min": 4.81,
    "humidity": 40,
    "feels_like": 0.08,
    "pressure": 1017,
    "rain_mm": 0
  },
  {
    "time": "2026-01-28 21:00:00",
    "temp": 4.36,
    "temp_max": 4.36,
    "temp_min": 4.36,
    "humidity": 39,
    "feels_like": 0.05,
    "pressure": 1018,
    "rain_mm": 0
  },
  {
    "time": "2026-01-29 00:00:00",
    "temp": 4.58,
    "temp_max": 4.58,
    "temp_min": 4.58,
    "humidity": 37,
    "feels_like": 0.63,
    "pressure": 1018,
    "rain_mm": 0
  },
  {
    "time": "2026-01-29 03:00:00",
    "temp": 6.01,
    "temp_max": 6.01,
    "temp_min": 6.01,
    "humidity": 31,
    "feels_like": 3.01,
    "pressure": 1017,
    "rain_mm": 0
  },
  {
    "time": "2026-01-29 06:00:00",
    "temp": 6.49,
    "temp_max": 6.49,
    "temp_min": 6.49,
    "humidity": 33,
    "feels_like": 6.49,
    "pressure": 1016,
    "rain_mm": 0
  },
  {
    "time": "2026-01-29 09:00:00",
    "temp": 6.22,
    "temp_max": 6.22,
    "temp_min": 6.22,
    "humidity": 41,
    "feels_like": 6.22,
    "pressure": 1016,
    "rain_mm": 0
  },
  {
    "time": "2026-01-29 12:00:00",
    "temp": 6.02,
    "temp_max": 6.02,
    "temp_min": 6.02,
    "humidity": 54,
    "feels_like": 2.87,
    "pressure": 1016,
    "rain_mm": 0.2
  },
  {
    "time": "2026-01-29 15:00:00",
    "temp": 5.21,
    "temp_max": 5.21,
    "temp_min": 5.21,
    "humidity": 40,
    "feels_like": 0.29,
    "pressure": 1016,
    "rain_mm": 0.22
  },
  {
    "time": "2026-01-29 18:00:00",
    "temp": 4.53,
    "temp_max": 4.53,
    "temp_min": 4.53,
    "humidity": 41,
    "feels_like": 0.25,
    "pressure": 1017,
    "rain_mm": 0
  },
  {
    "time": "2026-01-29 21:00:00",
    "temp": 3.84,
    "temp_max": 3.84,
    "temp_min": 3.84,
    "humidity": 43,
    "feels_like": -0.47,
    "pressure": 1018,
    "rain_mm": 0
  },
  {
    "time": "2026-01-30 00:00:00",
    "temp": 3.7,
    "temp_max": 3.7,
    "temp_min": 3.7,
    "humidity": 42,
    "feels_like": 0.55,
    "pressure": 1019,
    "rain_mm": 0
  },
  {
    "time": "2026-01-30 03:00:00",
    "temp": 5.62,
    "temp_max": 5.62,
    "temp_min": 5.62,
    "humidity": 33,
    "feels_like": 4.42,
    "pressure": 1017,
    "rain_mm": 0
  },
  {
    "time": "2026-01-30 06:00:00",
    "temp": 5.7,
    "temp_max": 5.7,
    "temp_min": 5.7,
    "humidity": 50,
    "feels_like": 2.76,
    "pressure": 1016,
    "rain_mm": 0.18
  },
  {
    "time": "2026-01-30 09:00:00",
    "temp": 6.18,
    "temp_max": 6.18,
    "temp_min": 6.18,
    "humidity": 50,
    "feels_like": 2.59,
    "pressure": 1017,
    "rain_mm": 0.14
  },
  {
    "time": "2026-01-30 12:00:00",
    "temp": 5.58,
    "temp_max": 5.58,
    "temp_min": 5.58,
    "humidity": 37,
    "feels_like": 1.27,
    "pressure": 1017,
    "rain_mm": 0
  },
  {
    "time": "2026-01-30 15:00:00",
    "temp": 4.53,
    "temp_max": 4.53,
    "temp_min": 4.53,
    "humidity": 34,
    "feels_like": 0.04,
    "pressure": 1016,
    "rain_mm": 0
  },
  {
    "time": "2026-01-30 18:00:00",
    "temp": 3.8,
    "temp_max": 3.8,
    "temp_min": 3.8,
    "humidity": 40,
    "feels_like": -0.55,
    "pressure": 1017,
    "rain_mm": 0
  },
  {
    "time": "2026-01-30 21:00:00",
    "temp": 3.3,
    "temp_max": 3.3,
    "temp_min": 3.3,
    "humidity": 38,
    "feels_like": -1.09,
    "pressure": 1017,
    "rain_mm": 0
  },
  {
    "time": "2026-01-31 00:00:00",
    "temp": 3.41,
    "temp_max": 3.41,
    "temp_min": 3.41,
    "humidity": 33,
    "feels_like": 0.32,
    "pressure": 1019,
    "rain_mm": 0
  },
  {
    "time": "2026-01-31 03:00:00",
    "temp": 4.93,
    "temp_max": 4.93,
    "temp_min": 4.93,
    "humidity": 34,
    "feels_like": 4.93,
    "pressure": 1017,
    "rain_mm": 0
  },
  {
    "time": "2026-01-31 06:00:00",
    "temp": 5.87,
    "temp_max": 5.87,
    "temp_min": 5.87,
    "humidity": 47,
    "feels_like": 4.19,
    "pressure": 1017,
    "rain_mm": 0
  },
  {
    "time": "2026-01-31 09:00:00",
    "temp": 6.18,
    "temp_max": 6.18,
    "temp_min": 6.18,
    "humidity": 43,
    "feels_like": 4.23,
    "pressure": 1018,
    "rain_mm": 0
  },
  {
    "time": "2026-01-31 12:00:00",
    "temp": 6.51,
    "temp_max": 6.51,
    "temp_min": 6.51,
    "humidity": 42,
    "feels_like": 6.51,
    "pressure": 1018,
    "rain_mm": 0
  },
  {
    "time": "2026-01-31 15:00:00",
    "temp": 5.67,
    "temp_max": 5.67,
    "temp_min": 5.67,
    "humidity": 43,
    "feels_like": 2.65,
    "pressure": 1018,
    "rain_mm": 0
  },
  {
    "time": "2026-01-31 18:00:00",
    "temp": 4.91,
    "temp_max": 4.91,
    "temp_min": 4.91,
    "humidity": 39,
    "feels_like": 2.05,
    "pressure": 1018,
    "rain_mm": 0
  },
  {
    "time": "2026-01-31 21:00:00",
    "temp": 4.58,
    "temp_max": 4.58,
    "temp_min": 4.58,
    "humidity": 39,
    "feels_like": 2.4,
    "pressure": 1018,
    "rain_mm": 0
  },
  {
    "time": "2026-02-01 00:00:00",
    "temp": 4.66,
    "temp_max": 4.66,
    "temp_min": 4.66,
    "humidity": 40,
    "feels_like": 3.36,
    "pressure": 1018,
    "rain_mm": 0
  },
  {
    "time": "2026-02-01 03:00:00",
    "temp": 5.85,
    "temp_max": 5.85,
    "temp_min": 5.85,
    "humidity": 39,
    "feels_like": 5.85,
    "pressure": 1016,
    "rain_mm": 0
  },
  {
    "time": "2026-02-01 06:00:00",
    "temp": 7.05,
    "temp_max": 7.05,
    "temp_min": 7.05,
    "humidity": 40,
    "feels_like": 5.73,
    "pressure": 1015,
    "rain_mm": 0
  },
  {
    "time": "2026-02-01 09:00:00",
    "temp": 7.53,
    "temp_max": 7.53,
    "temp_min": 7.53,
    "humidity": 40,
    "feels_like": 6.42,
    "pressure": 1016,
    "rain_mm": 0
  },
  {
    "time": "2026-02-01 12:00:00",
    "temp": 7.75,
    "temp_max": 7.75,
    "temp_min": 7.75,
    "humidity": 39,
    "feels_like": 7.01,
    "pressure": 1016,
    "rain_mm": 0
  },
  {
    "time": "2026-02-01 15:00:00",
    "temp": 7.15,
    "temp_max": 7.15,
    "temp_min": 7.15,
    "humidity": 44,
    "feels_like": 5,
    "pressure": 1015,
    "rain_mm": 0
  },
  {
    "time": "2026-02-01 18:00:00",
    "temp": 5.93,
    "temp_max": 5.93,
    "temp_min": 5.93,
    "humidity": 46,
    "feels_like": 3.32,
    "pressure": 1015,
    "rain_mm": 0
  },
  {
    "time": "2026-02-01 21:00:00",
    "temp": 5.06,
    "temp_max": 5.06,
    "temp_min": 5.06,
    "humidity": 48,
    "feels_like": 2.74,
    "pressure": 1015,
    "rain_mm": 0
  },
  {
    "time": "2026-02-02 00:00:00",
    "temp": 5.45,
    "temp_max": 5.45,
    "temp_min": 5.45,
    "humidity": 47,
    "feels_like": 3.23,
    "pressure": 1015,
    "rain_mm": 0
  },
  {
    "time": "2026-02-02 03:00:00",
    "temp": 7.03,
    "temp_max": 7.03,
    "temp_min": 7.03,
    "humidity": 46,
    "feels_like": 5.29,
    "pressure": 1013,
    "rain_mm": 0
  }
]