[
  {
    "time": "2025-12-21 18:00:00",
    "temp": 12.46,
    "temp_max": 12.46,
    "temp_min": 11.81,
    "humidity": 67,
    "feels_like": 11.51,
    "pressure": 1014,
    "weather_main": "Clouds",
    "weather_description": "broken clouds",
    "weather_icon": "04n",
    "rain_mm": 0,
    "snow_mm": 0
  },
  {
    "time": "2025-12-21 21:00:00",
    "temp": 11.55,
    "temp_max": 11.55,
    "temp_min": 10.94,
    "humidity": 58,
    "feels_like": 10.28,
    "pressure": 1017,
    "weather_main": "Clouds",
    "weather_description": "overcast clouds",
    "weather_icon": "04n",
    "rain_mm": 0,
    "snow_mm": 0
  }
]