[
  {
    "time": "2025-12-31 18:00:00",
    "temp": 6.38,
    "temp_max": 7.95,
    "temp_min": 6.38,
    "humidity": 77,
    "feels_like": 2.39,
    "pressure": 1011,
    "weather_main": "Clouds",
    "weather_description": "broken clouds",
    "weather_icon": "04n",
    "rain_mm": 0,
    "snow_mm": 0
  },
  {
    "time": "2025-12-31 21:00:00",
    "temp": 6.58,
    "temp_max": 6.99,
    "temp_min": 6.58,
    "humidity": 71,
    "feels_like": 2.6,
    "pressure": 1011,
    "weather_main": "Clouds",
    "weather_description": "broken clouds",
    "weather_icon": "04n",
    "rain_mm": 0,
    "snow_mm": 0
  }
]