[
  {
    "time": "2025-10-15 15:00:00",
    "temp": 18.2,
    "temp_max": 19.97,
    "temp_min": 18.2,
    "humidity": 85,
    "feels_like": 18.3,
    "pressure": 1022,
    "weather_main": "Clouds",
    "weather_description": "broken clouds",
    "weather_icon": "04n",
    "rain_mm": 0,
    "snow_mm": 0
  },
  {
    "time": "2025-10-15 18:00:00",
    "temp": 18.42,
    "temp_max": 18.86,
    "temp_min": 18.42,
    "humidity": 84,
    "feels_like": 18.51,
    "pressure": 1022,
    "weather_main": "Rain",
    "weather_description": "light rain",
    "weather_icon": "10n",
    "rain_mm": 0.92,
    "snow_mm": 0
  },
  {
    "time": "2025-10-15 21:00:00",
    "temp": 18.47,
    "temp_max": 18.6,
    "temp_min": 18.47,
    "humidity": 86,
    "feels_like": 18.62,
    "pressure": 1021,
    "weather_main": "Rain",
    "weather_description": "light rain",
    "weather_icon": "10d",
    "rain_mm": 2.09,
    "snow_mm": 0
  }
]