[
  {
    "time": "2026-02-17 18:00:00",
    "temp": 6.66,
    "temp_max": 6.89,
    "temp_min": 6.66,
    "humidity": 80,
    "feels_like": 4.48,
    "pressure": 1016,
    "weather_main": "Rain",
    "weather_description": "light rain",
    "weather_icon": "10n",
    "rain_mm": 0.77,
    "snow_mm": 0
  },
  {
    "time": "2026-02-17 21:00:00",
    "temp": 6.82,
    "temp_max": 6.95,
    "temp_min": 6.82,
    "humidity": 75,
    "feels_like": 4.47,
    "pressure": 1015,
    "weather_main": "Clouds",
    "weather_description": "overcast clouds",
    "weather_icon": "04n",
    "rain_mm": 0,
    "snow_mm": 0
  }
]