[
  {
    "time": "2025-11-21 03:00:00",
    "temp": 14.29,
    "temp_max": 14.29,
    "temp_min": 13.74,
    "humidity": 65,
    "feels_like": 13.47,
    "pressure": 1015,
    "weather_main": "Clear",
    "weather_description": "clear sky",
    "weather_icon": "01d",
    "rain_mm": 0,
    "snow_mm": 0
  },
  {
    "time": "2025-11-21 06:00:00",
    "temp": 14.59,
    "temp_max": 15.2,
    "temp_min": 14.59,
    "humidity": 57,
    "feels_like": 13.59,
    "pressure": 1014,
    "weather_main": "Clear",
    "weather_description": "clear sky",
    "weather_icon": "01d",
    "rain_mm": 0,
    "snow_mm": 0
  },
  {
    "time": "2025-11-21 09:00:00",
    "temp": 15.7,
    "temp_max": 16.4,
    "temp_min": 15.7,
    "humidity": 51,
    "feels_like": 14.66,
    "pressure": 1014,
    "weather_main": "Clear",
    "weather_description": "clear sky",
    "weather_icon": "01n",
    "rain_mm": 0,
    "snow_mm": 0
  },
  {
    "time": "2025-11-21 12:00:00",
    "temp": 15.83,
    "temp_max": 15.83,
    "temp_min": 15.83,
    "humidity": 40,
    "feels_like": 14.51,
    "pressure": 1016,
    "weather_main": "Clear",
    "weather_description": "clear sky",
    "weather_icon": "01n",
    "rain_mm": 0,
    "snow_mm": 0
  },
  {
    "time": "2025-11-21 15:00:00",
    "temp": 14.35,
    "temp_max": 14.35,
    "temp_min": 14.35,
    "humidity": 51,
    "feels_like": 13.17,
    "pressure": 1017,
    "weather_main": "Clear",
    "weather_description": "clear sky",
    "weather_icon": "01n",
    "rain_mm": 0,
    "snow_mm": 0
  },
  {
    "time": "2025-11-21 18:00:00",
    "temp": 13.4,
    "temp_max": 13.4,
    "temp_min": 13.4,
    "humidity": 55,
    "feels_like": 12.23,
    "pressure": 1019,
    "weather_main": "Clear",
    "weather_description": "clear sky",
    "weather_icon": "01n",
    "rain_mm": 0,
    "snow_mm": 0
  },
  {
    "time": "2025-11-21 21:00:00",
    "temp": 12.28,
    "temp_max": 12.28,
    "temp_min": 12.28,
    "humidity": 62,
    "feels_like": 11.18,
    "pressure": 1021,
    "weather_main": "Clear",
    "weather_description": "clear sky",
    "weather_icon": "01n",
    "rain_mm": 0,
    "snow_mm": 0
  }
]