[
  {
    "time": "2026-04-07 06:00:00",
    "temp": 16.83,
    "temp_max": 16.83,
    "temp_min": 15.92,
    "humidity": 86,
    "feels_like": 16.81,
    "pressure": 1000,
    "weather_main": "Rain",
    "weather_description": "light rain",
    "weather_icon": "10d",
    "rain_mm": 1.06,
    "snow_mm": 0
  },
  {
    "time": "2026-04-07 09:00:00",
    "temp": 14.12,
    "temp_max": 14.12,
    "temp_min": 12.54,
    "humidity": 63,
    "feels_like": 13.23,
    "pressure": 1001,
    "weather_main": "Rain",
    "weather_description": "light rain",
    "weather_icon": "10d",
    "rain_mm": 0.17,
    "snow_mm": 0
  },
  {
    "time": "2026-04-07 12:00:00",
    "temp": 11.63,
    "temp_max": 11.63,
    "temp_min": 11.63,
    "humidity": 44,
    "feels_like": 10,
    "pressure": 1006,
    "weather_main": "Rain",
    "weather_description": "light rain",
    "weather_icon": "10n",
    "rain_mm": 0.1,
    "snow_mm": 0
  },
  {
    "time": "2026-04-07 15:00:00",
    "temp": 10.73,
    "temp_max": 10.73,
    "temp_min": 10.73,
    "humidity": 38,
    "feels_like": 8.85,
    "pressure": 1009,
    "weather_main": "Clouds",
    "weather_description": "broken clouds",
    "weather_icon": "04n",
    "rain_mm": 0,
    "snow_mm": 0
  },
  {
    "time": "2026-04-07 18:00:00",
    "temp": 10.01,
    "temp_max": 10.01,
    "temp_min": 10.01,
    "humidity": 37,
    "feels_like": 8.03,
    "pressure": 1012,
    "weather_main": "Clouds",
    "weather_description": "broken clouds",
    "weather_icon": "04n",
    "rain_mm": 0,
    "snow_mm": 0
  },
  {
    "time": "2026-04-07 21:00:00",
    "temp": 9.62,
    "temp_max": 9.62,
    "temp_min": 9.62,
    "humidity": 39,
    "feels_like": 5.73,
    "pressure": 1016,
    "weather_main": "Clear",
    "weather_description": "clear sky",
    "weather_icon": "01d",
    "rain_mm": 0,
    "snow_mm": 0
  }
]