[
  {
    "time": "2026-01-26 18:00:00",
    "temp": 4.02,
    "temp_max": 4.02,
    "temp_min": 2.72,
    "humidity": 48,
    "feels_like": -0.93,
    "pressure": 1016,
    "weather_main": "Rain",
    "weather_description": "light rain",
    "weather_icon": "10n",
    "rain_mm": 2.31,
    "snow_mm": 0
  },
  {
    "time": "2026-01-26 21:00:00",
    "temp": 4.17,
    "temp_max": 4.46,
    "temp_min": 4.17,
    "humidity": 48,
    "feels_like": 0.35,
    "pressure": 1016,
    "weather_main": "Clouds",
    "weather_description": "broken clouds",
    "weather_icon": "04n",
    "rain_mm": 0,
    "snow_mm": 0
  }
]