[
  {
    "time": "2026-05-30 18:00:00",
    "temp": 22.17,
    "temp_max": 22.17,
    "temp_min": 21.79,
    "humidity": 79,
    "feels_like": 22.51,
    "pressure": 1012,
    "weather_main": "Clear",
    "weather_description": "clear sky",
    "weather_icon": "01n",
    "rain_mm": 0,
    "snow_mm": 0
  },
  {
    "time": "2026-05-30 21:00:00",
    "temp": 21.94,
    "temp_max": 21.94,
    "temp_min": 21.47,
    "humidity": 77,
    "feels_like": 22.2,
    "pressure": 1013,
    "weather_main": "Clouds",
    "weather_description": "scattered clouds",
    "weather_icon": "03d",
    "rain_mm": 0,
    "snow_mm": 0
  }
]