[
  {
    "time": "2025-11-26 15:00:00",
    "wind_speed": 20.1,
    "wind_gust": 21.1,
    "pressure": 1004,
    "lat": 35.0,
    "lon": 150.0,
    "region": "Pacific Ocean",
    "in_japan": true,
    "temp": 16.11,
    "humidity": 76,
    "weather_main": "Rain",
    "weather_description": "light rain",
    "rain_mm": 2.38
  },
  {
    "time": "2025-11-28 12:00:00",
    "wind_speed": 18.06,
    "wind_gust": 22.2,
    "pressure": 1009,
    "lat": 35.0,
    "lon": 150.0,
    "region": "Pacific Ocean",
    "in_japan": true,
    "temp": 17.95,
    "humidity": 89,
    "weather_main": "Rain",
    "weather_description": "moderate rain",
    "rain_mm": 7.44
  },
  {
    "time": "2025-11-28 18:00:00",
    "wind_speed": 18.02,
    "wind_gust": 23.41,
    "pressure": 1007,
    "lat": 40.0,
    "lon": 155.0,
    "region": "Pacific Ocean",
    "in_japan": false,
    "temp": 14.82,
    "humidity": 81,
    "weather_main": "Rain",
    "weather_description": "light rain",
    "rain_mm": 1.06
  }
]